MANIFEST.in
README.md
setup.py
imrt_qa_data_miner.egg-info/PKG-INFO
imrt_qa_data_miner.egg-info/SOURCES.txt
imrt_qa_data_miner.egg-info/dependency_links.txt
imrt_qa_data_miner.egg-info/entry_points.txt
imrt_qa_data_miner.egg-info/requires.txt
imrt_qa_data_miner.egg-info/top_level.txt
src/__init__.py
src/main.py
src/pdf_to_text.py
src/qa_parser.py