Metadata-Version: 1.1
Name: imrt-qa-data-miner
Version: 0.1.3
Summary: Scans a directory for SNC Patient IMRT QA results
Home-page: https://github.com/cutright/IMRT-QA-Data-Miner/
Author: Dan Cutright
Author-email: dan.cutright@gmail.com
License: MIT License
Download-URL: https://github.com/cutright/IMRT-QA-Data-Miner/archive/master.zip
Keywords: radiation therapy,qa,research
Platform: UNKNOWN
